gecosistema_colab/__init__.py
gecosistema_colab/utils.py
gecosistema_colab-0.0.14.dist-info/METADATA
gecosistema_colab-0.0.14.dist-info/RECORD
gecosistema_colab-0.0.14.dist-info/WHEEL
gecosistema_colab-0.0.14.dist-info/top_level.txt
