Metadata-Version: 2.1
Name: gecosistema-colab
Version: 0.0.14
Summary: A small example package
Home-page: https://github.com/valluzzi/gecosistema_colab.git
Author: Valerio Luzzi
Author-email: valluzzi@gmail.com
License: UNKNOWN
Platform: UNKNOWN
Classifier: Programming Language :: Python :: 2
Classifier: License :: OSI Approved :: MIT License
Classifier: Operating System :: OS Independent
Requires-Dist: google
Requires-Dist: matplotlib
